s_dbw/__init__.py
s_dbw/s_dbw.py
s_dbw-0.4.0.dist-info/LICENSE
s_dbw-0.4.0.dist-info/METADATA
s_dbw-0.4.0.dist-info/WHEEL
s_dbw-0.4.0.dist-info/top_level.txt
s_dbw-0.4.0.dist-info/RECORD
